spikingjelly/__init__.py
spikingjelly/configure.py
spikingjelly/activation_based/__init__.py
spikingjelly/activation_based/base.py
spikingjelly/activation_based/cuda_utils.py
spikingjelly/activation_based/encoding.py
spikingjelly/activation_based/functional.py
spikingjelly/activation_based/lava_exchange.py
spikingjelly/activation_based/layer.py
spikingjelly/activation_based/learning.py
spikingjelly/activation_based/lynxi_exchange.py
spikingjelly/activation_based/monitor.py
spikingjelly/activation_based/neuron.py
spikingjelly/activation_based/neuron_kernel.py
spikingjelly/activation_based/quantize.py
spikingjelly/activation_based/rnn.py
spikingjelly/activation_based/spike_op.py
spikingjelly/activation_based/surrogate.py
spikingjelly/activation_based/tensor_cache.py
spikingjelly/activation_based/ann2snn/__init__.py
spikingjelly/activation_based/ann2snn/converter.py
spikingjelly/activation_based/ann2snn/modules.py
spikingjelly/activation_based/ann2snn/utils.py
spikingjelly/activation_based/ann2snn/examples/__init__.py
spikingjelly/activation_based/ann2snn/examples/cnn_mnist.py
spikingjelly/activation_based/ann2snn/examples/resnet18_cifar10.py
spikingjelly/activation_based/auto_cuda/__init__.py
spikingjelly/activation_based/auto_cuda/base.py
spikingjelly/activation_based/auto_cuda/cfunction.py
spikingjelly/activation_based/auto_cuda/example.py
spikingjelly/activation_based/auto_cuda/generator.py
spikingjelly/activation_based/auto_cuda/neuron_kernel.py
spikingjelly/activation_based/examples/A2C.py
spikingjelly/activation_based/examples/DQN_state.py
spikingjelly/activation_based/examples/PPO.py
spikingjelly/activation_based/examples/Spiking_A2C.py
spikingjelly/activation_based/examples/Spiking_DQN_state.py
spikingjelly/activation_based/examples/Spiking_PPO.py
spikingjelly/activation_based/examples/__init__.py
spikingjelly/activation_based/examples/cifar10_r11_enabling_spikebased_backpropagation.py
spikingjelly/activation_based/examples/classify_dvsg.py
spikingjelly-0.0.0.0.14.dist-info/LICENSE
spikingjelly-0.0.0.0.14.dist-info/LICENSE-CN
spikingjelly-0.0.0.0.14.dist-info/METADATA
spikingjelly-0.0.0.0.14.dist-info/WHEEL
spikingjelly-0.0.0.0.14.dist-info/top_level.txt
spikingjelly-0.0.0.0.14.dist-info/RECORD
